{
    "characters": [
        {
            "name": "dimeng",
            "displayName": "Demon",
            "rank": "S",
            "libram": "ANGER",
            "tendency": "Endura",
            "category": "Sinners",
            "attires": [
                {
                    "name": "default",
                    "displayName": "Default"
                },
                {
                    "name": "under_the_neon_lights",
                    "displayName": "Under the Neon Lights"
                }
            ]
        },
        {
            "name": "owo",
            "displayName": "OwO",
            "rank": "S",
            "libram": "SLOTH",
            "tendency": "Endura",
            "category": "Sinners",
            "attires": [
                {
                    "name": "default",
                    "displayName": "Default"
                },
                {
                    "name": "king_of_lion_dance",
                    "displayName": "King of Lion Dance"
                },
                {
                    "name": "auspicious_prancer",
                    "displayName": "Auspicious Prancer"
                }
            ]
        },
        {
            "name": "rahu",
            "displayName": "Rahu",
            "rank": "S",
            "libram": "ANGER",
            "tendency": "Endura",
            "category": "Sinners",
            "attires": [
                {
                    "name": "default",
                    "displayName": "Default"
                },
                {
                    "name": "radiant_stealth",
                    "displayName": "Radiant Stealth"
                },
                {
                    "name": "loyal_oath",
                    "displayName": "Loyal Oath"
                }
            ]
        },
        {
            "name": "vanilla",
            "displayName": "Vanilla",
            "rank": "S",
            "libram": "IMMORTAL",
            "tendency": "Endura",
            "category": "Sinners",
            "attires": [
                {
                    "name": "default",
                    "displayName": "Default"
                },
                {
                    "name": "vanilla_-_initial",
                    "displayName": "Vanilla - Initial"
                },
                {
                    "name": "aether_runner",
                    "displayName": "Aether Runner"
                }
            ]
        },
        {
            "name": "moore",
            "displayName": "Moore",
            "rank": "S",
            "libram": "PESTILENCE",
            "tendency": "Endura",
            "category": "Sinners",
            "attires": [
                {
                    "name": "default",
                    "displayName": "Default"
                },
                {
                    "name": "ensnaring_eclipse",
                    "displayName": "Ensnaring Eclipse"
                }
            ]
        },
        {
            "name": "yugu",
            "displayName": "Yugu",
            "rank": "S",
            "libram": "FRAUD",
            "tendency": "Endura",
            "category": "Sinners",
            "attires": [
                {
                    "name": "default",
                    "displayName": "Default"
                },
                {
                    "name": "celestial_augury",
                    "displayName": "Celestial Augury"
                }
            ]
        },
        {
            "name": "rust",
            "displayName": "Rust",
            "rank": "S",
            "libram": "TREACHERY",
            "tendency": "Endura",
            "category": "Sinners",
            "attires": [
                {
                    "name": "default",
                    "displayName": "Default"
                }
            ]
        },
        {
            "name": "zoya",
            "displayName": "Zoya",
            "rank": "S",
            "libram": "VIOLENCE",
            "tendency": "Fury",
            "category": "Sinners",
            "attires": [
                {
                    "name": "default",
                    "displayName": "Default"
                },
                {
                    "name": "wolves_strike_soon",
                    "displayName": "Wolves Strike Soon"
                },
                {
                    "name": "supreme_negotiation",
                    "displayName": "Supreme Negotiation"
                },
                {
                    "name": "lord_of_rimehowl",
                    "displayName": "Lord of Rimehowl"
                }
            ]
        },
        {
            "name": "nuokesi",
            "displayName": "NOX",
            "rank": "S",
            "libram": "LIMBO",
            "tendency": "Fury",
            "category": "Sinners",
            "attires": [
                {
                    "name": "default",
                    "displayName": "Default"
                },
                {
                    "name": "ashen_prayer",
                    "displayName": "Ashen Prayer"
                },
                {
                    "name": "gloom_of_daybreak",
                    "displayName": "Gloom of Daybreak"
                },
                {
                    "name": "into_the_tinted_dawn",
                    "displayName": "Into the Tinted Dawn"
                }
            ]
        },
        {
            "name": "deren",
            "displayName": "Deren",
            "rank": "S",
            "libram": "FRAUD",
            "tendency": "Fury",
            "category": "Sinners",
            "attires": [
                {
                    "name": "default",
                    "displayName": "Default"
                },
                {
                    "name": "eclat_eminence",
                    "displayName": "Eclat Eminence"
                },
                {
                    "name": "butterfly_shadow",
                    "displayName": "Butterfly Shadow"
                }
            ]
        },
        {
            "name": "don",
            "displayName": "Donald",
            "rank": "S",
            "libram": "TREACHERY",
            "tendency": "Fury",
            "category": "Sinners",
            "attires": [
                {
                    "name": "default",
                    "displayName": "Default"
                },
                {
                    "name": "good_old_days",
                    "displayName": "Good Old Days"
                }
            ]
        },
        {
            "name": "yao",
            "displayName": "Yao",
            "rank": "S",
            "libram": "LIMBO",
            "tendency": "Fury",
            "category": "Sinners",
            "attires": [
                {
                    "name": "default",
                    "displayName": "Default"
                },
                {
                    "name": "yao_-_initial",
                    "displayName": "Yao - Initial"
                },
                {
                    "name": "fireborne_offering",
                    "displayName": "Fireborne Offering"
                }
            ]
        },
        {
            "name": "pylgia",
            "displayName": "Pylgia",
            "rank": "S",
            "libram": "IMMORTAL",
            "tendency": "Fury",
            "category": "Sinners",
            "attires": [
                {
                    "name": "default",
                    "displayName": "Default"
                },
                {
                    "name": "shackled_dream_in_aqua",
                    "displayName": "Shackled Dream in Aqua"
                }
            ]
        },
        {
            "name": "jotaro",
            "displayName": "Kujo Jotaro",
            "rank": "S",
            "libram": "INFINITE",
            "tendency": "Fury",
            "category": "Sinners",
            "attires": [
                {
                    "name": "default",
                    "displayName": "Default"
                }
            ]
        },
        {
            "name": "jasmine",
            "displayName": "Jasmine",
            "rank": "S",
            "libram": "WAR",
            "tendency": "Fury",
            "category": "Sinners",
            "attires": [
                {
                    "name": "default",
                    "displayName": "Default"
                },
                {
                    "name": "gossamer_sway",
                    "displayName": "Gossamer Sway"
                }
            ]
        },
        {
            "name": "synex",
            "displayName": "Synex",
            "rank": "S",
            "libram": "FAMINE",
            "tendency": "Fury",
            "category": "Sinners",
            "attires": [
                {
                    "name": "default",
                    "displayName": "Default"
                },
                {
                    "name": "street_striker",
                    "displayName": "Street Striker"
                }
            ]
        },
        {
            "name": "linglan",
            "displayName": "Bai Yi",
            "rank": "S",
            "libram": "TREACHERY",
            "tendency": "Umbra",
            "category": "Sinners",
            "attires": [
                {
                    "name": "default",
                    "displayName": "Default"
                },
                {
                    "name": "blade_of_night",
                    "displayName": "Blade of Night"
                },
                {
                    "name": "wave_rider",
                    "displayName": "Wave Rider"
                },
                {
                    "name": "aeon's_vanguard",
                    "displayName": "Aeon's Vanguard"
                }
            ]
        },
        {
            "name": "crache",
            "displayName": "Crache",
            "rank": "S",
            "libram": "LIMBO",
            "tendency": "Umbra",
            "category": "Sinners",
            "attires": [
                {
                    "name": "default",
                    "displayName": "Default"
                },
                {
                    "name": "eternal_night_hunt",
                    "displayName": "Eternal Night Hunt"
                },
                {
                    "name": "lucida_mystica",
                    "displayName": "Lucida Mystica"
                },
                {
                    "name": "shadow_groove",
                    "displayName": "Shadow Groove"
                }
            ]
        },
        {
            "name": "snake",
            "displayName": "Serpent",
            "rank": "S",
            "libram": "LOVE",
            "tendency": "Umbra",
            "category": "Sinners",
            "attires": [
                {
                    "name": "default",
                    "displayName": "Default"
                },
                {
                    "name": "awake_from_slumber",
                    "displayName": "Awake from Slumber"
                },
                {
                    "name": "source_of_happiness",
                    "displayName": "Source of Happiness"
                },
                {
                    "name": "elixir_of_euphoria",
                    "displayName": "Elixir of Euphoria"
                }
            ]
        },
        {
            "name": "adela",
            "displayName": "Adela",
            "rank": "S",
            "libram": "SLOTH",
            "tendency": "Umbra",
            "category": "Sinners",
            "attires": [
                {
                    "name": "default",
                    "displayName": "Default"
                },
                {
                    "name": "candlelit_turret",
                    "displayName": "Candlelit Turret"
                },
                {
                    "name": "woodland_wanderer",
                    "displayName": "Woodland Wanderer"
                }
            ]
        },
        {
            "name": "mantis",
            "displayName": "Mantis",
            "rank": "S",
            "libram": "IMMORTAL",
            "tendency": "Umbra",
            "category": "Sinners",
            "attires": [
                {
                    "name": "default",
                    "displayName": "Default"
                },
                {
                    "name": "sylvan_silhouette",
                    "displayName": "Sylvan Silhouette"
                }
            ]
        },
        {
            "name": "angel",
            "displayName": "Angell",
            "rank": "S",
            "libram": "PESTILENCE",
            "tendency": "Umbra",
            "category": "Sinners",
            "attires": [
                {
                    "name": "default",
                    "displayName": "Default"
                },
                {
                    "name": "lurking_lotusblade",
                    "displayName": "Lurking Lotusblade"
                },
                {
                    "name": "thunder_beat",
                    "displayName": "Thunder Beat"
                }
            ]
        },
        {
            "name": "jolyne",
            "displayName": "Jolyne Cujoh",
            "rank": "S",
            "libram": "INFINITE",
            "tendency": "Umbra",
            "category": "Sinners",
            "attires": [
                {
                    "name": "default",
                    "displayName": "Default"
                }
            ]
        },
        {
            "name": "zero",
            "displayName": "000",
            "rank": "S",
            "libram": "PESTILENCE",
            "tendency": "Umbra",
            "category": "Sinners",
            "attires": [
                {
                    "name": "default",
                    "displayName": "Default"
                },
                {
                    "name": "xenospace_pythoness",
                    "displayName": "Xenospace Pythoness"
                },
                {
                    "name": "amped_frenzy",
                    "displayName": "Amped Frenzy"
                }
            ]
        },
        {
            "name": "graves",
            "displayName": "Graves",
            "rank": "S",
            "libram": "DEATH",
            "tendency": "Umbra",
            "category": "Sinners",
            "attires": [
                {
                    "name": "default",
                    "displayName": "Default"
                },
                {
                    "name": "reverie_belle",
                    "displayName": "Reverie Belle"
                }
            ]
        },
        {
            "name": "hellasp",
            "displayName": "Necresta·Hella",
            "rank": "S",
            "libram": "FAMINE",
            "tendency": "Umbra",
            "category": "Sinners",
            "attires": [
                {
                    "name": "default",
                    "displayName": "Default"
                }
            ]
        },
        {
            "name": "ceto",
            "displayName": "Ceto",
            "rank": "S",
            "libram": "WAR",
            "tendency": "Umbra",
            "category": "Sinners",
            "attires": [
                {
                    "name": "default",
                    "displayName": "Default"
                }
            ]
        },
        {
            "name": "hitomi",
            "displayName": "Kisugi Hitomi",
            "rank": "S",
            "libram": "INFINITE",
            "tendency": "Umbra",
            "category": "Sinners",
            "attires": [
                {
                    "name": "default",
                    "displayName": "Default"
                },
                {
                    "name": "neon_raindrops",
                    "displayName": "Neon Raindrops"
                }
            ]
        },
        {
            "name": "xiayin",
            "displayName": "Summer",
            "rank": "S",
            "libram": "HERESY",
            "tendency": "Reticle",
            "category": "Sinners",
            "attires": [
                {
                    "name": "default",
                    "displayName": "Default"
                },
                {
                    "name": "desert_delusions",
                    "displayName": "Desert Delusions"
                },
                {
                    "name": "luminous_night",
                    "displayName": "Luminous Night"
                }
            ]
        },
        {
            "name": "lanli",
            "displayName": "Langley",
            "rank": "S",
            "libram": "TREACHERY",
            "tendency": "Reticle",
            "category": "Sinners",
            "attires": [
                {
                    "name": "default",
                    "displayName": "Default"
                },
                {
                    "name": "banquet_guest",
                    "displayName": "Banquet Guest"
                },
                {
                    "name": "madame_maelstrom",
                    "displayName": "Madame Maelstrom"
                }
            ]
        },
        {
            "name": "oak",
            "displayName": "Oak Casket",
            "rank": "S",
            "libram": "SLOTH",
            "tendency": "Reticle",
            "category": "Sinners",
            "attires": [
                {
                    "name": "default",
                    "displayName": "Default"
                },
                {
                    "name": "forest_of_enthrallment",
                    "displayName": "Forest of Enthrallment"
                },
                {
                    "name": "sepulchral_ride",
                    "displayName": "Sepulchral Ride"
                }
            ]
        },
        {
            "name": "dreya",
            "displayName": "Dreya",
            "rank": "S",
            "libram": "IMMORTAL",
            "tendency": "Reticle",
            "category": "Sinners",
            "attires": [
                {
                    "name": "default",
                    "displayName": "Default"
                },
                {
                    "name": "cosmic_escapist",
                    "displayName": "Cosmic Escapist"
                },
                {
                    "name": "seastral_starlight",
                    "displayName": "Seastral Starlight"
                }
            ]
        },
        {
            "name": "shalom",
            "displayName": "Shalom",
            "rank": "S",
            "libram": "SLOTH",
            "tendency": "Reticle",
            "category": "Sinners",
            "attires": [
                {
                    "name": "default",
                    "displayName": "Default"
                },
                {
                    "name": "city_never_sleeps",
                    "displayName": "City Never Sleeps"
                },
                {
                    "name": "undawning_nighttide",
                    "displayName": "Undawning Nighttide"
                }
            ]
        },
        {
            "name": "pearl",
            "displayName": "Lady Pearl",
            "rank": "S",
            "libram": "SLOTH",
            "tendency": "Reticle",
            "category": "Sinners",
            "attires": [
                {
                    "name": "default",
                    "displayName": "Default"
                },
                {
                    "name": "lady_pearl_-_initial",
                    "displayName": "Lady Pearl - Initial"
                },
                {
                    "name": "glorious_spectacle_unfolds",
                    "displayName": "Glorious Spectacle Unfolds"
                }
            ]
        },
        {
            "name": "bianca",
            "displayName": "Bianca",
            "rank": "S",
            "libram": "PESTILENCE",
            "tendency": "Reticle",
            "category": "Sinners",
            "attires": [
                {
                    "name": "default",
                    "displayName": "Default"
                },
                {
                    "name": "in-cider_scoop",
                    "displayName": "In-Cider Scoop"
                },
                {
                    "name": "bouncing_toccata",
                    "displayName": "Bouncing Toccata"
                }
            ]
        },
        {
            "name": "korryn",
            "displayName": "Korryn",
            "rank": "S",
            "libram": "FAMINE",
            "tendency": "Reticle",
            "category": "Sinners",
            "attires": [
                {
                    "name": "default",
                    "displayName": "Default"
                },
                {
                    "name": "aureate_ambush",
                    "displayName": "Aureate Ambush"
                }
            ]
        },
        {
            "name": "hypatia",
            "displayName": "Hypatia",
            "rank": "S",
            "libram": "FAMINE",
            "tendency": "Reticle",
            "category": "Sinners",
            "attires": [
                {
                    "name": "default",
                    "displayName": "Default"
                },
                {
                    "name": "crepuscular_bloom",
                    "displayName": "Crepuscular Bloom"
                }
            ]
        },
        {
            "name": "augustus",
            "displayName": "Augustus",
            "rank": "S",
            "libram": "WAR",
            "tendency": "Reticle",
            "category": "Sinners",
            "attires": [
                {
                    "name": "default",
                    "displayName": "Default"
                }
            ]
        },
        {
            "name": "heli",
            "displayName": "Eirene",
            "rank": "S",
            "libram": "GREED",
            "tendency": "Arcane",
            "category": "Sinners",
            "attires": [
                {
                    "name": "default",
                    "displayName": "Default"
                },
                {
                    "name": "seaside_sunrise",
                    "displayName": "Seaside Sunrise"
                },
                {
                    "name": "daughter_of_fraser_city",
                    "displayName": "Daughter of Fraser City"
                },
                {
                    "name": "veil_of_flame",
                    "displayName": "Veil of Flame"
                }
            ]
        },
        {
            "name": "anarkia",
            "displayName": "Stargazer",
            "rank": "S",
            "libram": "HERESY",
            "tendency": "Arcane",
            "category": "Sinners",
            "attires": [
                {
                    "name": "default",
                    "displayName": "Default"
                },
                {
                    "name": "moonlit_enchantment",
                    "displayName": "Moonlit Enchantment"
                },
                {
                    "name": "sunfall_prophecy",
                    "displayName": "Sunfall Prophecy"
                }
            ]
        },
        {
            "name": "etti",
            "displayName": "Etti",
            "rank": "S",
            "libram": "FRAUD",
            "tendency": "Arcane",
            "category": "Sinners",
            "attires": [
                {
                    "name": "default",
                    "displayName": "Default"
                },
                {
                    "name": "noctivagation",
                    "displayName": "Noctivagation"
                },
                {
                    "name": "dances_&_dragons",
                    "displayName": "Dances & Dragons"
                }
            ]
        },
        {
            "name": "raven",
            "displayName": "Raven",
            "rank": "S",
            "libram": "FRAUD",
            "tendency": "Arcane",
            "category": "Sinners",
            "attires": [
                {
                    "name": "default",
                    "displayName": "Default"
                },
                {
                    "name": "arnheim_athenaeum",
                    "displayName": "Arnheim Athenaeum"
                },
                {
                    "name": "raven_in_the_box",
                    "displayName": "Raven in the Box"
                }
            ]
        },
        {
            "name": "eleven",
            "displayName": "Eleven",
            "rank": "S",
            "libram": "SLOTH",
            "tendency": "Arcane",
            "category": "Sinners",
            "attires": [
                {
                    "name": "default",
                    "displayName": "Default"
                },
                {
                    "name": "rippling_heartthrobs",
                    "displayName": "Rippling Heartthrobs"
                },
                {
                    "name": "trickling_heartstream",
                    "displayName": "Trickling Heartstream"
                }
            ]
        },
        {
            "name": "hestia",
            "displayName": "Hestia",
            "rank": "S",
            "libram": "IMMORTAL",
            "tendency": "Arcane",
            "category": "Sinners",
            "attires": [
                {
                    "name": "default",
                    "displayName": "Default"
                },
                {
                    "name": "lambent_wishbearer",
                    "displayName": "Lambent Wishbearer"
                },
                {
                    "name": "dusk_aglow",
                    "displayName": "Dusk Aglow"
                }
            ]
        },
        {
            "name": "vautour",
            "displayName": "Vautour Bleu",
            "rank": "S",
            "libram": "FAMINE",
            "tendency": "Arcane",
            "category": "Sinners",
            "attires": [
                {
                    "name": "default",
                    "displayName": "Default"
                },
                {
                    "name": "languor_en_bleu",
                    "displayName": "Languor en Bleu"
                },
                {
                    "name": "vin_nocturne",
                    "displayName": "Vin Nocturne"
                }
            ]
        },
        {
            "name": "yingying",
            "displayName": "Yingying",
            "rank": "S",
            "libram": "LOVE",
            "tendency": "Arcane",
            "category": "Sinners",
            "attires": [
                {
                    "name": "default",
                    "displayName": "Default"
                },
                {
                    "name": "fluttered_heartstrings",
                    "displayName": "Fluttered Heartstrings"
                }
            ]
        },
        {
            "name": "milly",
            "displayName": "Milly",
            "rank": "S",
            "libram": "DEATH",
            "tendency": "Arcane",
            "category": "Sinners",
            "attires": [
                {
                    "name": "default",
                    "displayName": "Default"
                },
                {
                    "name": "timeless_silhouette",
                    "displayName": "Timeless Silhouette"
                }
            ]
        },
        {
            "name": "hilda",
            "displayName": "Hilda",
            "rank": "S",
            "libram": "SEQUESTER",
            "tendency": "Arcane",
            "category": "Sinners",
            "attires": [
                {
                    "name": "default",
                    "displayName": "Default"
                }
            ]
        },
        {
            "name": "rui",
            "displayName": "Kisugi Rui",
            "rank": "S",
            "libram": "INFINITE",
            "tendency": "Arcane",
            "category": "Sinners",
            "attires": [
                {
                    "name": "default",
                    "displayName": "Default"
                },
                {
                    "name": "tipsy_nocturne",
                    "displayName": "Tipsy Nocturne"
                }
            ]
        },
        {
            "name": "hameier",
            "displayName": "Hamel",
            "rank": "S",
            "libram": "LOVE",
            "tendency": "Catalyst",
            "category": "Sinners",
            "attires": [
                {
                    "name": "default",
                    "displayName": "Default"
                },
                {
                    "name": "joyful_tune",
                    "displayName": "Joyful Tune"
                },
                {
                    "name": "odile",
                    "displayName": "Odile"
                },
                {
                    "name": "azure_waltz_in_solace",
                    "displayName": "Azure Waltz in Solace"
                }
            ]
        },
        {
            "name": "enfer",
            "displayName": "Enfer",
            "rank": "S",
            "libram": "LIMBO",
            "tendency": "Catalyst",
            "category": "Sinners",
            "attires": [
                {
                    "name": "default",
                    "displayName": "Default"
                },
                {
                    "name": "sculptor's_nest",
                    "displayName": "Sculptor's Nest"
                },
                {
                    "name": "virtuoso_of_jade",
                    "displayName": "Virtuoso of Jade"
                }
            ]
        },
        {
            "name": "cab",
            "displayName": "Cabernet",
            "rank": "S",
            "libram": "SLOTH",
            "tendency": "Catalyst",
            "category": "Sinners",
            "attires": [
                {
                    "name": "default",
                    "displayName": "Default"
                },
                {
                    "name": "bacchanal_reverie",
                    "displayName": "Bacchanal Reverie"
                },
                {
                    "name": "intoxication_à_deux",
                    "displayName": "Intoxication à Deux"
                },
                {
                    "name": "crimson_prologue",
                    "displayName": "Crimson Prologue"
                }
            ]
        },
        {
            "name": "coquelicot",
            "displayName": "Coquelic",
            "rank": "S",
            "libram": "LIMBO",
            "tendency": "Catalyst",
            "category": "Sinners",
            "attires": [
                {
                    "name": "default",
                    "displayName": "Default"
                },
                {
                    "name": "blossom",
                    "displayName": "Blossom"
                },
                {
                    "name": "crimson_hunt",
                    "displayName": "Crimson Hunt"
                }
            ]
        },
        {
            "name": "eve",
            "displayName": "Eve",
            "rank": "S",
            "libram": "LOVE",
            "tendency": "Catalyst",
            "category": "Sinners",
            "attires": [
                {
                    "name": "default",
                    "displayName": "Default"
                },
                {
                    "name": "agleam_escapade",
                    "displayName": "Agleam Escapade"
                },
                {
                    "name": "frostling_whisper",
                    "displayName": "Frostling Whisper"
                }
            ]
        },
        {
            "name": "duruo",
            "displayName": "Du Ruo",
            "rank": "S",
            "libram": "FRAUD",
            "tendency": "Catalyst",
            "category": "Sinners",
            "attires": [
                {
                    "name": "default",
                    "displayName": "Default"
                },
                {
                    "name": "du_ruo_-_initial",
                    "displayName": "Du Ruo - Initial"
                },
                {
                    "name": "lunaria_enigma",
                    "displayName": "Lunaria Enigma"
                },
                {
                    "name": "breezy_embrace",
                    "displayName": "Breezy Embrace"
                }
            ]
        },
        {
            "name": "ll",
            "displayName": "L.L.",
            "rank": "S",
            "libram": "PESTILENCE",
            "tendency": "Catalyst",
            "category": "Sinners",
            "attires": [
                {
                    "name": "default",
                    "displayName": "Default"
                },
                {
                    "name": "astral_rhapsody",
                    "displayName": "Astral Rhapsody"
                }
            ]
        },
        {
            "name": "jelena",
            "displayName": "Jelena",
            "rank": "S",
            "libram": "FAMINE",
            "tendency": "Catalyst",
            "category": "Sinners",
            "attires": [
                {
                    "name": "default",
                    "displayName": "Default"
                },
                {
                    "name": "scorched_lullaby",
                    "displayName": "Scorched Lullaby"
                }
            ]
        },
        {
            "name": "parfait",
            "displayName": "Parfait",
            "rank": "S",
            "libram": "DEATH",
            "tendency": "Catalyst",
            "category": "Sinners",
            "attires": [
                {
                    "name": "default",
                    "displayName": "Default"
                },
                {
                    "name": "salon_rosé",
                    "displayName": "Salon Rosé"
                }
            ]
        },
        {
            "name": "shin",
            "displayName": "Shin",
            "rank": "S",
            "libram": "IMMORTAL",
            "tendency": "Catalyst",
            "category": "Sinners",
            "attires": [
                {
                    "name": "default",
                    "displayName": "Default"
                },
                {
                    "name": "stellar_embrace",
                    "displayName": "Stellar Embrace"
                }
            ]
        },
        {
            "name": "irrheia",
            "displayName": "Irrheia",
            "rank": "S",
            "libram": "FRAUD",
            "tendency": "Catalyst",
            "category": "Sinners",
            "attires": [
                {
                    "name": "default",
                    "displayName": "Default"
                }
            ]
        },
        {
            "name": "margaret",
            "displayName": "Margaret",
            "rank": "S",
            "libram": "DEATH",
            "tendency": "Catalyst",
            "category": "Sinners",
            "attires": [
                {
                    "name": "default",
                    "displayName": "Default"
                }
            ]
        },
        {
            "name": "fupo",
            "displayName": "Countess Chelsea",
            "rank": "A",
            "libram": "GREED",
            "tendency": "Endura",
            "category": "Sinners",
            "attires": [
                {
                    "name": "default",
                    "displayName": "Default"
                },
                {
                    "name": "moonlight_rendezvous",
                    "displayName": "Moonlight Rendezvous"
                },
                {
                    "name": "lake_of_mythos",
                    "displayName": "Lake of Mythos"
                }
            ]
        },
        {
            "name": "beisefenni",
            "displayName": "Cinnabar",
            "rank": "A",
            "libram": "TREACHERY",
            "tendency": "Endura",
            "category": "Sinners",
            "attires": [
                {
                    "name": "default",
                    "displayName": "Default"
                },
                {
                    "name": "special_escort",
                    "displayName": "Special Escort"
                },
                {
                    "name": "courteous_call",
                    "displayName": "Courteous Call"
                }
            ]
        },
        {
            "name": "kavakava",
            "displayName": "Kawa-kawa",
            "rank": "A",
            "libram": "HERESY",
            "tendency": "Endura",
            "category": "Sinners",
            "attires": [
                {
                    "name": "default",
                    "displayName": "Default"
                },
                {
                    "name": "down_the_rabbit_hole",
                    "displayName": "Down the Rabbit Hole"
                }
            ]
        },
        {
            "name": "levy",
            "displayName": "Levy",
            "rank": "A",
            "libram": "GREED",
            "tendency": "Endura",
            "category": "Sinners",
            "attires": [
                {
                    "name": "default",
                    "displayName": "Default"
                },
                {
                    "name": "twilight_thrills",
                    "displayName": "Twilight Thrills"
                }
            ]
        },
        {
            "name": "uni",
            "displayName": "Uni",
            "rank": "A",
            "libram": "LOVE",
            "tendency": "Endura",
            "category": "Sinners",
            "attires": [
                {
                    "name": "default",
                    "displayName": "Default"
                },
                {
                    "name": "guise_into_life",
                    "displayName": "Guise into Life"
                }
            ]
        },
        {
            "name": "nino",
            "displayName": "Nino",
            "rank": "A",
            "libram": "LIMBO",
            "tendency": "Endura",
            "category": "Sinners",
            "attires": [
                {
                    "name": "default",
                    "displayName": "Default"
                },
                {
                    "name": "nino_sama:_schoolgoing",
                    "displayName": "Nino Sama: Schoolgoing"
                }
            ]
        },
        {
            "name": "golem",
            "displayName": "Golan",
            "rank": "A",
            "libram": "PESTILENCE",
            "tendency": "Endura",
            "category": "Sinners",
            "attires": [
                {
                    "name": "default",
                    "displayName": "Default"
                },
                {
                    "name": "rooftop_reckoning",
                    "displayName": "Rooftop Reckoning"
                }
            ]
        },
        {
            "name": "dove",
            "displayName": "Dove",
            "rank": "A",
            "libram": "FAMINE",
            "tendency": "Endura",
            "category": "Sinners",
            "attires": [
                {
                    "name": "default",
                    "displayName": "Default"
                }
            ]
        },
        {
            "name": "anasui",
            "displayName": "Narciso Anastasia",
            "rank": "A",
            "libram": "INFINITE",
            "tendency": "Endura",
            "category": "Sinners",
            "attires": [
                {
                    "name": "default",
                    "displayName": "Default"
                }
            ]
        },
        {
            "name": "luminita",
            "displayName": "Luminita",
            "rank": "A",
            "libram": "SLOTH",
            "tendency": "Endura",
            "category": "Sinners",
            "attires": [
                {
                    "name": "default",
                    "displayName": "Default"
                }
            ]
        },
        {
            "name": "siglinde",
            "displayName": "Siglinde",
            "rank": "A",
            "libram": "WAR",
            "tendency": "Endura",
            "category": "Sinners",
            "attires": [
                {
                    "name": "default",
                    "displayName": "Default"
                }
            ]
        },
        {
            "name": "rumina",
            "displayName": "Rumina",
            "rank": "A",
            "libram": "LOVE",
            "tendency": "Endura",
            "category": "Sinners",
            "attires": [
                {
                    "name": "default",
                    "displayName": "Default"
                }
            ]
        },
        {
            "name": "jiushijiu",
            "displayName": "Ninety-Nine",
            "rank": "A",
            "libram": "VIOLENCE",
            "tendency": "Fury",
            "category": "Sinners",
            "attires": [
                {
                    "name": "default",
                    "displayName": "Default"
                },
                {
                    "name": "chaotic_restraint",
                    "displayName": "Chaotic Restraint"
                },
                {
                    "name": "new_world",
                    "displayName": "New World"
                }
            ]
        },
        {
            "name": "wendy",
            "displayName": "Wendy",
            "rank": "A",
            "libram": "VIOLENCE",
            "tendency": "Fury",
            "category": "Sinners",
            "attires": [
                {
                    "name": "default",
                    "displayName": "Default"
                },
                {
                    "name": "chainsaw_nightmare",
                    "displayName": "Chainsaw Nightmare"
                },
                {
                    "name": "elegy_of_the_rust",
                    "displayName": "Elegy of the Rust"
                }
            ]
        },
        {
            "name": "pajiaxi",
            "displayName": "Pacassi",
            "rank": "A",
            "libram": "LOVE",
            "tendency": "Fury",
            "category": "Sinners",
            "attires": [
                {
                    "name": "default",
                    "displayName": "Default"
                },
                {
                    "name": "winter_night",
                    "displayName": "Winter Night"
                },
                {
                    "name": "frostforged_maiden",
                    "displayName": "Frostforged Maiden"
                }
            ]
        },
        {
            "name": "duoli",
            "displayName": "Dolly",
            "rank": "A",
            "libram": "VIOLENCE",
            "tendency": "Fury",
            "category": "Sinners",
            "attires": [
                {
                    "name": "default",
                    "displayName": "Default"
                },
                {
                    "name": "sunset_swing",
                    "displayName": "Sunset Swing"
                }
            ]
        },
        {
            "name": "mojila",
            "displayName": "Horo",
            "rank": "A",
            "libram": "ANGER",
            "tendency": "Fury",
            "category": "Sinners",
            "attires": [
                {
                    "name": "default",
                    "displayName": "Default"
                },
                {
                    "name": "limit_breaker",
                    "displayName": "Limit Breaker"
                },
                {
                    "name": "abiding_moment",
                    "displayName": "Abiding Moment"
                }
            ]
        },
        {
            "name": "mess",
            "displayName": "Mess",
            "rank": "A",
            "libram": "HERESY",
            "tendency": "Fury",
            "category": "Sinners",
            "attires": [
                {
                    "name": "default",
                    "displayName": "Default"
                },
                {
                    "name": "mystic_pawnshop",
                    "displayName": "Mystic Pawnshop"
                }
            ]
        },
        {
            "name": "corso",
            "displayName": "Corso",
            "rank": "A",
            "libram": "VIOLENCE",
            "tendency": "Fury",
            "category": "Sinners",
            "attires": [
                {
                    "name": "default",
                    "displayName": "Default"
                },
                {
                    "name": "suit-up_outlaw",
                    "displayName": "Suit-up Outlaw"
                }
            ]
        },
        {
            "name": "christina",
            "displayName": "Christina",
            "rank": "A",
            "libram": "ANGER",
            "tendency": "Fury",
            "category": "Sinners",
            "attires": [
                {
                    "name": "default",
                    "displayName": "Default"
                },
                {
                    "name": "sunrise_express",
                    "displayName": "Sunrise Express"
                }
            ]
        },
        {
            "name": "rise",
            "displayName": "Rise",
            "rank": "A",
            "libram": "PESTILENCE",
            "tendency": "Fury",
            "category": "Sinners",
            "attires": [
                {
                    "name": "default",
                    "displayName": "Default"
                },
                {
                    "name": "nebula_sentinel",
                    "displayName": "Nebula Sentinel"
                }
            ]
        },
        {
            "name": "mira",
            "displayName": "Mira",
            "rank": "A",
            "libram": "FAMINE",
            "tendency": "Fury",
            "category": "Sinners",
            "attires": [
                {
                    "name": "default",
                    "displayName": "Default"
                }
            ]
        },
        {
            "name": "ermes",
            "displayName": "Ermes Costello",
            "rank": "S",
            "libram": "INFINITE",
            "tendency": "Fury",
            "category": "Sinners",
            "attires": [
                {
                    "name": "default",
                    "displayName": "Default"
                }
            ]
        },
        {
            "name": "lysandra",
            "displayName": "Lysandra",
            "rank": "A",
            "libram": "VIOLENCE",
            "tendency": "Fury",
            "category": "Sinners",
            "attires": [
                {
                    "name": "default",
                    "displayName": "Default"
                }
            ]
        },
        {
            "name": "ark",
            "displayName": "Ark",
            "rank": "A",
            "libram": "LOVE",
            "tendency": "Fury",
            "category": "Sinners",
            "attires": [
                {
                    "name": "default",
                    "displayName": "Default"
                }
            ]
        },
        {
            "name": "xinxiya",
            "displayName": "Iron",
            "rank": "A",
            "libram": "ANGER",
            "tendency": "Umbra",
            "category": "Sinners",
            "attires": [
                {
                    "name": "default",
                    "displayName": "Default"
                },
                {
                    "name": "dr._ironstein",
                    "displayName": "Dr. Ironstein"
                }
            ]
        },
        {
            "name": "tetra",
            "displayName": "Tetra",
            "rank": "A",
            "libram": "GREED",
            "tendency": "Umbra",
            "category": "Sinners",
            "attires": [
                {
                    "name": "default",
                    "displayName": "Default"
                },
                {
                    "name": "edge_of_nightfall",
                    "displayName": "Edge of Nightfall"
                }
            ]
        },
        {
            "name": "jin",
            "displayName": "Sumire",
            "rank": "A",
            "libram": "LOVE",
            "tendency": "Umbra",
            "category": "Sinners",
            "attires": [
                {
                    "name": "default",
                    "displayName": "Default"
                },
                {
                    "name": "flower_of_fantasy",
                    "displayName": "Flower of Fantasy"
                },
                {
                    "name": "moonrise_fondness",
                    "displayName": "Moonrise Fondness"
                }
            ]
        },
        {
            "name": "mcqueen",
            "displayName": "McQueen",
            "rank": "A",
            "libram": "TREACHERY",
            "tendency": "Umbra",
            "category": "Sinners",
            "attires": [
                {
                    "name": "default",
                    "displayName": "Default"
                },
                {
                    "name": "inferno_of_deception",
                    "displayName": "Inferno of Deception"
                },
                {
                    "name": "whimsical_theater",
                    "displayName": "Whimsical Theater"
                }
            ]
        },
        {
            "name": "lynn",
            "displayName": "Lynn",
            "rank": "A",
            "libram": "SLOTH",
            "tendency": "Umbra",
            "category": "Sinners",
            "attires": [
                {
                    "name": "default",
                    "displayName": "Default"
                },
                {
                    "name": "skittish_star",
                    "displayName": "Skittish Star"
                }
            ]
        },
        {
            "name": "garofano",
            "displayName": "Garofano",
            "rank": "A",
            "libram": "SLOTH",
            "tendency": "Umbra",
            "category": "Sinners",
            "attires": [
                {
                    "name": "default",
                    "displayName": "Default"
                },
                {
                    "name": "in_the_veiled_grove",
                    "displayName": "In the Veiled Grove"
                }
            ]
        },
        {
            "name": "eureka",
            "displayName": "Eureka",
            "rank": "A",
            "libram": "LIMBO",
            "tendency": "Umbra",
            "category": "Sinners",
            "attires": [
                {
                    "name": "default",
                    "displayName": "Default"
                },
                {
                    "name": "eureka_in_meowingtons",
                    "displayName": "Eureka in Meowingtons"
                }
            ]
        },
        {
            "name": "thistle",
            "displayName": "Thistle",
            "rank": "A",
            "libram": "LOVE",
            "tendency": "Umbra",
            "category": "Sinners",
            "attires": [
                {
                    "name": "default",
                    "displayName": "Default"
                },
                {
                    "name": "thistle_-_initial",
                    "displayName": "Thistle - Initial"
                },
                {
                    "name": "oneiric_flexagon",
                    "displayName": "Oneiric Flexagon"
                }
            ]
        },
        {
            "name": "shrooma",
            "displayName": "Shrooma",
            "rank": "A",
            "libram": "PESTILENCE",
            "tendency": "Umbra",
            "category": "Sinners",
            "attires": [
                {
                    "name": "default",
                    "displayName": "Default"
                },
                {
                    "name": "whimsy_escape",
                    "displayName": "Whimsy Escape"
                }
            ]
        },
        {
            "name": "poffy",
            "displayName": "Poffy",
            "rank": "A",
            "libram": "SLOTH",
            "tendency": "Umbra",
            "category": "Sinners",
            "attires": [
                {
                    "name": "default",
                    "displayName": "Default"
                }
            ]
        },
        {
            "name": "peggi",
            "displayName": "Pricilla",
            "rank": "A",
            "libram": "GREED",
            "tendency": "Reticle",
            "category": "Sinners",
            "attires": [
                {
                    "name": "default",
                    "displayName": "Default"
                },
                {
                    "name": "night_of_petals",
                    "displayName": "Night of Petals"
                },
                {
                    "name": "private_mischief",
                    "displayName": "Private Mischief"
                }
            ]
        },
        {
            "name": "kuangdu",
            "displayName": "Roulecca",
            "rank": "A",
            "libram": "ANGER",
            "tendency": "Reticle",
            "category": "Sinners",
            "attires": [
                {
                    "name": "default",
                    "displayName": "Default"
                },
                {
                    "name": "seaside_dessert_stand",
                    "displayName": "Seaside Dessert Stand"
                },
                {
                    "name": "puerile_maniac",
                    "displayName": "Puerile Maniac"
                }
            ]
        },
        {
            "name": "langhuan",
            "displayName": "Wolverine",
            "rank": "A",
            "libram": "VIOLENCE",
            "tendency": "Reticle",
            "category": "Sinners",
            "attires": [
                {
                    "name": "default",
                    "displayName": "Default"
                },
                {
                    "name": "summer_splash",
                    "displayName": "Summer Splash"
                }
            ]
        },
        {
            "name": "matilda",
            "displayName": "Matilda",
            "rank": "A",
            "libram": "SLOTH",
            "tendency": "Reticle",
            "category": "Sinners",
            "attires": [
                {
                    "name": "default",
                    "displayName": "Default"
                },
                {
                    "name": "elfin_siesta",
                    "displayName": "Elfin Siesta"
                }
            ]
        },
        {
            "name": "yanyan",
            "displayName": "Yanyan",
            "rank": "A",
            "libram": "HERESY",
            "tendency": "Reticle",
            "category": "Sinners",
            "attires": [
                {
                    "name": "default",
                    "displayName": "Default"
                },
                {
                    "name": "yanyan_-_initial",
                    "displayName": "Yanyan - Initial"
                },
                {
                    "name": "wafting_whimsy",
                    "displayName": "Wafting Whimsy"
                }
            ]
        },
        {
            "name": "ff",
            "displayName": "F.F.",
            "rank": "A",
            "libram": "INFINITE",
            "tendency": "Reticle",
            "category": "Sinners",
            "attires": [
                {
                    "name": "default",
                    "displayName": "Default"
                }
            ]
        },
        {
            "name": "jane",
            "displayName": "Jane",
            "rank": "A",
            "libram": "VIOLENCE",
            "tendency": "Reticle",
            "category": "Sinners",
            "attires": [
                {
                    "name": "default",
                    "displayName": "Default"
                },
                {
                    "name": "off-duty_summer_civvies",
                    "displayName": "Off-Duty Summer Civvies"
                }
            ]
        },
        {
            "name": "pine",
            "displayName": "Pine",
            "rank": "A",
            "libram": "PESTILENCE",
            "tendency": "Reticle",
            "category": "Sinners",
            "attires": [
                {
                    "name": "default",
                    "displayName": "Default"
                }
            ]
        },
        {
            "name": "thalia",
            "displayName": "Thalia",
            "rank": "A",
            "libram": "GREED",
            "tendency": "Reticle",
            "category": "Sinners",
            "attires": [
                {
                    "name": "default",
                    "displayName": "Default"
                }
            ]
        },
        {
            "name": "heerjia",
            "displayName": "Helga",
            "rank": "A",
            "libram": "FAMINE",
            "tendency": "Reticle",
            "category": "Sinners",
            "attires": [
                {
                    "name": "default",
                    "displayName": "Default"
                }
            ]
        },
        {
            "name": "bai",
            "displayName": "Victoria",
            "rank": "A",
            "libram": "LIMBO",
            "tendency": "Arcane",
            "category": "Sinners",
            "attires": [
                {
                    "name": "default",
                    "displayName": "Default"
                },
                {
                    "name": "good_morning,_medison",
                    "displayName": "Good Morning, Medison"
                },
                {
                    "name": "cocooned_serenade",
                    "displayName": "Cocooned Serenade"
                }
            ]
        },
        {
            "name": "eagle",
            "displayName": "Ignis",
            "rank": "A",
            "libram": "HERESY",
            "tendency": "Arcane",
            "category": "Sinners",
            "attires": [
                {
                    "name": "default",
                    "displayName": "Default"
                },
                {
                    "name": "warm_flame",
                    "displayName": "Warm Flame"
                },
                {
                    "name": "caramel_starwish",
                    "displayName": "Caramel Starwish"
                }
            ]
        },
        {
            "name": "luweiyalei",
            "displayName": "Luvia Ray",
            "rank": "A",
            "libram": "LIMBO",
            "tendency": "Arcane",
            "category": "Sinners",
            "attires": [
                {
                    "name": "default",
                    "displayName": "Default"
                },
                {
                    "name": "glittering_stars",
                    "displayName": "Glittering Stars"
                },
                {
                    "name": "beach_frolic",
                    "displayName": "Beach Frolic"
                }
            ]
        },
        {
            "name": "hekadi",
            "displayName": "Hecate",
            "rank": "A",
            "libram": "LIMBO",
            "tendency": "Arcane",
            "category": "Sinners",
            "attires": [
                {
                    "name": "default",
                    "displayName": "Default"
                },
                {
                    "name": "yesterday_revisits",
                    "displayName": "Yesterday Revisits"
                },
                {
                    "name": "traveler's_tale",
                    "displayName": "Traveler's Tale"
                },
                {
                    "name": "darkwing_eclipse",
                    "displayName": "Darkwing Eclipse"
                }
            ]
        },
        {
            "name": "olivier",
            "displayName": "Oliver",
            "rank": "A",
            "libram": "TREACHERY",
            "tendency": "Arcane",
            "category": "Sinners",
            "attires": [
                {
                    "name": "default",
                    "displayName": "Default"
                },
                {
                    "name": "haloed_refrain",
                    "displayName": "Haloed Refrain"
                }
            ]
        },
        {
            "name": "lamia",
            "displayName": "Lamia",
            "rank": "A",
            "libram": "HERESY",
            "tendency": "Arcane",
            "category": "Sinners",
            "attires": [
                {
                    "name": "default",
                    "displayName": "Default"
                },
                {
                    "name": "hushed_tides",
                    "displayName": "Hushed Tides"
                },
                {
                    "name": "drowning_lurve",
                    "displayName": "Drowning Lurve"
                }
            ]
        },
        {
            "name": "echo",
            "displayName": "Echo",
            "rank": "A",
            "libram": "FRAUD",
            "tendency": "Arcane",
            "category": "Sinners",
            "attires": [
                {
                    "name": "default",
                    "displayName": "Default"
                },
                {
                    "name": "echo_-_initial",
                    "displayName": "Echo - Initial"
                }
            ]
        },
        {
            "name": "weather",
            "displayName": "Weather Forecast",
            "rank": "A",
            "libram": "INFINITE",
            "tendency": "Arcane",
            "category": "Sinners",
            "attires": [
                {
                    "name": "default",
                    "displayName": "Default"
                }
            ]
        },
        {
            "name": "wuhuanzi",
            "displayName": "Wuhuanzi",
            "rank": "A",
            "libram": "SLOTH",
            "tendency": "Arcane",
            "category": "Sinners",
            "attires": [
                {
                    "name": "default",
                    "displayName": "Default"
                },
                {
                    "name": "verdant_apothecary",
                    "displayName": "Verdant Apothecary"
                }
            ]
        },
        {
            "name": "thani",
            "displayName": "Thani",
            "rank": "A",
            "libram": "FAMINE",
            "tendency": "Arcane",
            "category": "Sinners",
            "attires": [
                {
                    "name": "default",
                    "displayName": "Default"
                }
            ]
        },
        {
            "name": "airuier",
            "displayName": "Ariel",
            "rank": "A",
            "libram": "LOVE",
            "tendency": "Catalyst",
            "category": "Sinners",
            "attires": [
                {
                    "name": "default",
                    "displayName": "Default"
                },
                {
                    "name": "silent_nocturne",
                    "displayName": "Silent Nocturne"
                },
                {
                    "name": "cageling",
                    "displayName": "Cageling"
                }
            ]
        },
        {
            "name": "chameleon",
            "displayName": "Chameleon",
            "rank": "A",
            "libram": "HERESY",
            "tendency": "Catalyst",
            "category": "Sinners",
            "attires": [
                {
                    "name": "default",
                    "displayName": "Default"
                },
                {
                    "name": "message_in_dreams",
                    "displayName": "Message In Dreams"
                },
                {
                    "name": "dream's_ephemera",
                    "displayName": "Dream's Ephemera"
                }
            ]
        },
        {
            "name": "tuoqier",
            "displayName": "Anne",
            "rank": "A",
            "libram": "LOVE",
            "tendency": "Catalyst",
            "category": "Sinners",
            "attires": [
                {
                    "name": "default",
                    "displayName": "Default"
                },
                {
                    "name": "steamy_night_chat",
                    "displayName": "Steamy Night Chat"
                },
                {
                    "name": "glistening_raindrops",
                    "displayName": "Glistening Raindrops"
                }
            ]
        },
        {
            "name": "kaier",
            "displayName": "Mr. Fox",
            "rank": "A",
            "libram": "GREED",
            "tendency": "Catalyst",
            "category": "Sinners",
            "attires": [
                {
                    "name": "default",
                    "displayName": "Default"
                },
                {
                    "name": "twilight_game",
                    "displayName": "Twilight Game"
                }
            ]
        },
        {
            "name": "dudu",
            "displayName": "Dudu",
            "rank": "A",
            "libram": "SLOTH",
            "tendency": "Catalyst",
            "category": "Sinners",
            "attires": [
                {
                    "name": "default",
                    "displayName": "Default"
                },
                {
                    "name": "unsung_maestro",
                    "displayName": "Unsung Maestro"
                },
                {
                    "name": "bewitching_piper",
                    "displayName": "Bewitching Piper"
                }
            ]
        },
        {
            "name": "letta",
            "displayName": "Letta",
            "rank": "A",
            "libram": "FRAUD",
            "tendency": "Catalyst",
            "category": "Sinners",
            "attires": [
                {
                    "name": "default",
                    "displayName": "Default"
                },
                {
                    "name": "spectral_shenanigans",
                    "displayName": "Spectral Shenanigans"
                }
            ]
        },
        {
            "name": "cassia",
            "displayName": "Cassia",
            "rank": "A",
            "libram": "LOVE",
            "tendency": "Catalyst",
            "category": "Sinners",
            "attires": [
                {
                    "name": "default",
                    "displayName": "Default"
                },
                {
                    "name": "aromas_in_bloom",
                    "displayName": "Aromas in Bloom"
                }
            ]
        },
        {
            "name": "shawn",
            "displayName": "Shawn",
            "rank": "A",
            "libram": "FRAUD",
            "tendency": "Catalyst",
            "category": "Sinners",
            "attires": [
                {
                    "name": "default",
                    "displayName": "Default"
                },
                {
                    "name": "digital_fauxmance",
                    "displayName": "Digital Fauxmance"
                }
            ]
        },
        {
            "name": "zephyr",
            "displayName": "Zephyr",
            "rank": "A",
            "libram": "LOVE",
            "tendency": "Catalyst",
            "category": "Sinners",
            "attires": [
                {
                    "name": "default",
                    "displayName": "Default"
                }
            ]
        },
        {
            "name": "cassian",
            "displayName": "Cassian",
            "rank": "A",
            "libram": "SLOTH",
            "tendency": "Catalyst",
            "category": "Sinners",
            "attires": [
                {
                    "name": "default",
                    "displayName": "Default"
                }
            ]
        },
        {
            "name": "ai",
            "displayName": "Kisugi Ai",
            "rank": "A",
            "libram": "INFINITE",
            "tendency": "Catalyst",
            "category": "Sinners",
            "attires": [
                {
                    "name": "default",
                    "displayName": "Default"
                },
                {
                    "name": "tender_signal",
                    "displayName": "Tender Signal"
                }
            ]
        },
        {
            "name": "kk",
            "displayName": "K.K.",
            "rank": "B",
            "libram": "VIOLENCE",
            "tendency": "Endura",
            "category": "Sinners",
            "attires": [
                {
                    "name": "default",
                    "displayName": "Default"
                },
                {
                    "name": "undercover_fill-in",
                    "displayName": "Undercover Fill-in"
                }
            ]
        },
        {
            "name": "atlant",
            "displayName": "Demolia",
            "rank": "B",
            "libram": "LIMBO",
            "tendency": "Endura",
            "category": "Sinners",
            "attires": [
                {
                    "name": "default",
                    "displayName": "Default"
                },
                {
                    "name": "gritty_detour",
                    "displayName": "Gritty Detour"
                }
            ]
        },
        {
            "name": "qiao",
            "displayName": "Peggy",
            "rank": "B",
            "libram": "GREED",
            "tendency": "Endura",
            "category": "Sinners",
            "attires": [
                {
                    "name": "default",
                    "displayName": "Default"
                },
                {
                    "name": "sensory_hyperwave",
                    "displayName": "Sensory Hyperwave"
                }
            ]
        },
        {
            "name": "hella",
            "displayName": "Hella",
            "rank": "B",
            "libram": "VIOLENCE",
            "tendency": "Fury",
            "category": "Sinners",
            "attires": [
                {
                    "name": "default",
                    "displayName": "Default"
                },
                {
                    "name": "queen_of_hearts",
                    "displayName": "Queen of Hearts"
                },
                {
                    "name": "food_tour",
                    "displayName": "Food Tour"
                },
                {
                    "name": "northward_to_whitesands",
                    "displayName": "Northward to WhiteSands"
                }
            ]
        },
        {
            "name": "che",
            "displayName": "Che",
            "rank": "B",
            "libram": "LIMBO",
            "tendency": "Fury",
            "category": "Sinners",
            "attires": [
                {
                    "name": "default",
                    "displayName": "Default"
                },
                {
                    "name": "unexpected_guest",
                    "displayName": "Unexpected Guest"
                }
            ]
        },
        {
            "name": "jiekuilin",
            "displayName": "Pepper",
            "rank": "B",
            "libram": "GREED",
            "tendency": "Fury",
            "category": "Sinners",
            "attires": [
                {
                    "name": "default",
                    "displayName": "Default"
                },
                {
                    "name": "peppy_shepherdess",
                    "displayName": "Peppy Shepherdess"
                }
            ]
        },
        {
            "name": "renou",
            "displayName": "Labyrinth",
            "rank": "B",
            "libram": "ANGER",
            "tendency": "Umbra",
            "category": "Sinners",
            "attires": [
                {
                    "name": "default",
                    "displayName": "Default"
                },
                {
                    "name": "fortune_and_prosperity",
                    "displayName": "Fortune and Prosperity"
                }
            ]
        },
        {
            "name": "zuoyi",
            "displayName": "Gekkabijin",
            "rank": "B",
            "libram": "LOVE",
            "tendency": "Umbra",
            "category": "Sinners",
            "attires": [
                {
                    "name": "default",
                    "displayName": "Default"
                }
            ]
        },
        {
            "name": "aimiliya",
            "displayName": "EMP",
            "rank": "B",
            "libram": "TREACHERY",
            "tendency": "Reticle",
            "category": "Sinners",
            "attires": [
                {
                    "name": "default",
                    "displayName": "Default"
                },
                {
                    "name": "backstreet_overlord",
                    "displayName": "Backstreet Overlord"
                },
                {
                    "name": "hail_from_the_otaku_world",
                    "displayName": "Hail from the Otaku World"
                }
            ]
        },
        {
            "name": "fuluola",
            "displayName": "Flora",
            "rank": "B",
            "libram": "TREACHERY",
            "tendency": "Reticle",
            "category": "Sinners",
            "attires": [
                {
                    "name": "default",
                    "displayName": "Default"
                },
                {
                    "name": "fire_safety_tips",
                    "displayName": "Fire Safety Tips"
                }
            ]
        },
        {
            "name": "dina",
            "displayName": "Kelvin",
            "rank": "B",
            "libram": "TREACHERY",
            "tendency": "Arcane",
            "category": "Sinners",
            "attires": [
                {
                    "name": "default",
                    "displayName": "Default"
                },
                {
                    "name": "chilling_hideaway",
                    "displayName": "Chilling Hideaway"
                }
            ]
        },
        {
            "name": "geji",
            "displayName": "Joan",
            "rank": "B",
            "libram": "ANGER",
            "tendency": "Arcane",
            "category": "Sinners",
            "attires": [
                {
                    "name": "default",
                    "displayName": "Default"
                },
                {
                    "name": "backstage_break",
                    "displayName": "Backstage Break"
                }
            ]
        },
        {
            "name": "aida",
            "displayName": "Macchiato",
            "rank": "B",
            "libram": "HERESY",
            "tendency": "Catalyst",
            "category": "Sinners",
            "attires": [
                {
                    "name": "default",
                    "displayName": "Default"
                },
                {
                    "name": "beguiled_heart",
                    "displayName": "Beguiled Heart"
                }
            ]
        },
        {
            "name": "monalisa",
            "displayName": "Lisa",
            "rank": "B",
            "libram": "HERESY",
            "tendency": "Catalyst",
            "category": "Sinners",
            "attires": [
                {
                    "name": "default",
                    "displayName": "Default"
                },
                {
                    "name": "trail_of_butterfly",
                    "displayName": "Trail of Butterfly"
                }
            ]
        }
    ]
}