{
    "default": [
        {
            "title": "수감자 획득",
            "filename": "File:vo_cab_cacha_001.aac",
            "text": "날 이 성대한 연회장에 데려와 줘서 고마워~ 아… 이곳은 구석구석까지 빠져들 것 같은 달콤한 향기가 가득해!"
        },
        {
            "title": "1급으로 승급",
            "filename": "File:vo_cab_promotion_001.aac",
            "text": "겨우 이 정도라면, 난 만족할 수 없어…"
        },
        {
            "title": "3급으로 승급",
            "filename": "File:vo_cab_promotion2_001.aac",
            "text": "최고의 맛을 위해서라면, 난 내 자신도 접시 위의 음식으로 내놓을 수 있어."
        },
        {
            "title": "스테이지 시작",
            "filename": "File:vo_cab_battlebegin_001.aac",
            "text": "어디 한번 음미해 볼까?"
        },
        {
            "title": "전투 승리",
            "filename": "File:vo_cab_battlewin_001.aac",
            "text": "괜찮은 식사 한 끼였어."
        },
        {
            "title": "전투 패배",
            "filename": "File:vo_cab_battlelose_001.aac",
            "text": "…너무 거북한 느낌이야."
        },
        {
            "title": "필살기",
            "filename": "File:bt_cab_uniqueskill_001.aac",
            "text": "영혼의 향기가 나잖아?"
        },
        {
            "title": "전투 중 사망",
            "filename": "File:bt_cab_dead_001.aac",
            "text": "하… 하하하… 찢어라, 삼켜라…"
        },
        {
            "title": "안부",
            "filename": "File:vo_cab_greeting_001.aac",
            "text": "초록색 요정이 날아가니, 현실이 펼쳐지고 그다음엔 공포가 보이더니, 마지막에는… 네가 보였어."
        },
        {
            "title": "대화1",
            "filename": "File:vo_cab_talk1_001.aac",
            "text": "음식을 먹는 건 단순히 '삼킨다'를 뜻하는 게 아니야. '음미'의 뜻을 깨우치게 되면, 음식을 먹는 건 아름다운 체험에 가깝지. 그러니까 솔직하게 식욕을 받아들이고 최대한 만족시켜 주라고!"
        },
        {
            "title": "대화2",
            "filename": "File:vo_cab_talk1_002.aac",
            "text": "굉장히 귀한 식자재를 많이 다뤄봤지. 그 중엔 집 한 채의 가치를 지닌 식자재도 있었어. 하지만… 내가 예전에 먹었던 그 달콤한 포도보다 맛있지는 않더라."
        },
        {
            "title": "대화3",
            "filename": "File:vo_cab_talk1_003.aac",
            "text": "높은 곳에 있는 사람은 안개 속에 갇혀 시야가 흐려지기 마련이지. 하지만 노력해서 찾아보면, 결국 빛나는 영혼을 가진 이들을 보게 될 수 있어."
        },
        {
            "title": "특별 대화1",
            "filename": "File:vo_cab_talk2_001.aac",
            "text": "난 항상 광적으로 열정을 다해 내 미각을 만족시킬 수 있는 것들을 추구했지. 마침 내가 가진 지위를 이용해 내 사심을 채울 수 있었어."
        },
        {
            "title": "특별 대화2",
            "filename": "File:vo_cab_talk2_002.aac",
            "text": "고상한 인간은 거부할 수 없는 매혹적인 냄새를 풍기지. 그들은 오래된 카베르네 프랑처럼 루비를 닮은 맛 좋은 와인을 빚어내서 나를 유혹하지."
        },
        {
            "title": "특별 대화3",
            "filename": "File:vo_cab_talk2_003.aac",
            "text": "따듯한 즙이 혀끝에서 시작되어 내 입안을 어루만지고, 식도를 넘어 천천히 뱃속으로 흘러들어와… 이게 바로 네가 내게 주는 느낌이야. 미안… 네 곁에 있는 것만으로는 충분하지 않은 것 같아. 난… 우리가 더 확실하게 하나가 되었으면 좋겠어."
        },
        {
            "title": "최대 복종도 달성",
            "filename": "File:vo_cab_obeyfull_001.aac",
            "text": "네 영혼에는 꿈과 현실이 섞여 있어. 예술과 인생이 무르익기 전에 난 이 초조하고 불안한 배고픔과 네 입꼬리에 입을 맞추고 싶은 충동을 참아낼 거야. 내 눈앞에서 이 매혹적인 과일이 다 자랄 때까지, 그리고 달갑게 나의 음미를 받아들일 때까지…"
        },
        {
            "title": "방치",
            "filename": "File:vo_cab_idle_001.aac",
            "text": "아… 식욕이 없네."
        },
        {
            "title": "초조",
            "filename": "File:vo_cab_clicking_001.aac",
            "text": "교활한 심연의 방문객은 언제나… 얌전하지 못한 그 녀석들을 잡아먹을 기회를 엿보고 있어."
        },
        {
            "title": "특별 주목",
            "filename": "File:vo_cab_specialattention_001.aac",
            "text": "너도 나와의 식사를 기대하나 보군, 그렇지?"
        },
        {
            "title": "파견",
            "filename": "File:vo_cab_dispatch_001.aac",
            "text": "이걸… 내가 직접 해야 해?"
        },
        {
            "title": "파견 완료",
            "filename": "File:vo_cab_dispatch2_001.aac",
            "text": "아주 신기한 경험이었어."
        },
        {
            "title": "레벨업",
            "filename": "File:vo_cab_levelup_002.aac",
            "text": "음~ 맛이 좋은걸?"
        },
        {
            "title": "머리 쓰다듬기",
            "filename": "File:vo_cab_head_001.aac",
            "text": "어떤 음식은 확실히 이 부위가 가장 맛있지. 너도 그렇게 생각해?"
        }
    ],
    "bacchanal_reverie": [
        {
            "title": "스킨 획득",
            "filename": "File:vo_cab_mingdingyoumeng_cacha_001.aac",
            "text": "극락과 풍요의 성지에 온 걸 환영해. 당신의 그 신선하고 독특한 영혼을 살찌울 수 있는 곳은 온 세상에 이곳밖에 없어… 자, 그럼 한잔할까?"
        },
        {
            "title": "레벨업",
            "filename": "File:vo_cab_mingdingyoumeng_levelup_001.aac",
            "text": "풍부한 과일 향이 입안에 가득 차는 이 느낌… 정말 좋은 술이야."
        },
        {
            "title": "안부",
            "filename": "File:vo_cab_mingdingyoumeng_greeting_001.aac",
            "text": "땅에서는 꿀이 샘솟고, 풍요의 뿔에서는 달콤한 넥타르가 넘쳐흐르지. 거기에 춤추는 천둥소리가 깃들면 한잔의 아름다운 와인이 되는 거야… 쭉 들이켜 봐, 넌 나와 함께 이제껏 맛보지 못했던 쾌락을 느끼게 될 거야~"
        },
        {
            "title": "머리 쓰다듬기",
            "filename": "File:vo_cab_mingdingyoumeng_head_001.aac",
            "text": "하하, 걱정할 필요 없어, 난 아직 멀쩡하거든. 스스로 잘 조절해야 약간 취한 상태에서 오는 쾌감을 마음껏 즐길 수 있지…"
        },
        {
            "title": "일반 터치1",
            "filename": "File:vo_cab_mingdingyoumeng_body_001.aac",
            "text": "뭘 망설이는 거야? 현실의 고민이 널 옭아맨다면, 그 귀여운 열매 하나를 먹어 봐. 그럼 고민을 잊고 무거운 짐을 내려놓을 수 있을 거야, 넌 분명… 좋아하게 될 거야."
        },
        {
            "title": "일반 터치2",
            "filename": "File:vo_cab_mingdingyoumeng_body_002.aac",
            "text": "쾌락을 거부할 수 있는 사람은 아무도 없어. 그들은 조금씩 자신도 모르는 사이에… 욕망에 휩싸이고, 혈관 속까지 와인이 가득 찬 채, 쾌락 속에 빠지고 말겠지. 그 또한 또 다른 퇴폐적이고 사치스러운 맛이 될 거야."
        },
        {
            "title": "일반 터치3",
            "filename": "File:vo_cab_mingdingyoumeng_hand_001.aac",
            "text": "너도 뭔가 부족한 느낌이 들어? 맞아, 최고의 음료는 최고의 음식과 함께 즐겨야 비로소 최상의 미각을 느낄 수 있지. 예를 들면, 너처럼 날카롭고 굳건한 영혼 말이야…"
        },
        {
            "title": "일반 터치4",
            "filename": "File:vo_cab_mingdingyoumeng_background_001.aac",
            "text": "사람에 비해 동물의 욕망은 정말 간단명료하지. 이 귀여운 녀석처럼 자신이 무얼 원하는지 분명히 알고 있어서 쉽게 만족하거든. 사람의 욕망은 오히려 복잡하고 끝이 없어… 이건 진화일까, 퇴화일까?"
        },
        {
            "title": "방치",
            "filename": "File:vo_cab_mingdingyoumeng_idle_001.aac",
            "text": "걱정하지 마, 재촉하지 않을게. 여긴 배고픔도 갈증도 없으니, 천천히 세세한 부분까지 음미해 보고 결정해도 돼. 가혹한 인간 세상과는 다르게… 이곳의 모든 것은 널 너그럽게 대해 줄 거야~"
        },
        {
            "title": "특별 주목",
            "filename": "File:vo_cab_mingdingyoumeng_specialattention_001.aac",
            "text": "내가 직접 나서길 바라는 거야? 이 아름다운 술과 열매에… 내 체온과 숨결이 더해지길 바라는구나~"
        }
    ],
    "intoxication_à_deux": [
        {
            "title": "스킨 획득",
            "filename": "File:vo_cab_gongzui_cacha_001.aac",
            "text": "서두르지 마, 자, 이걸 매… 음, 옥으로 만든 이 장식 덕분에 오늘 연회에 더욱 잘 어울려."
        },
        {
            "title": "레벨업",
            "filename": "File:vo_cab_gongzui_levelup_001.aac",
            "text": "옷차림이 과하지 않으면서도 품위가 있는 걸 보니… 꽤 애를 썼나 보군."
        },
        {
            "title": "안부",
            "filename": "File:vo_cab_gongzui_greeting_001.aac",
            "text": "하하, 긴장할 것 없어, 나와 함께 연회에 가는 거니까 이곳 음식이 얼마나 귀한지 신경 쓸 필요 없어. 그저 그 음식들이 네 마음속의 가장 원초적인 욕망을 느끼게 해줄 수 있는지만 신경 쓰면 돼~"
        },
        {
            "title": "일반 터치1",
            "filename": "File:vo_cab_gongzui_body_001.aac",
            "text": "유구한 역사를 지니고 있는 외부 도시에는 다양한 종류의 음식이 있다고 하는데, 눈앞에 있는 것들은 빙산의 일각에 불과해. 여기에 있는 진귀한 음식보다 더 훌륭한 음식이 얼마나 있을지… 기대하게 되네. 이런, 이렇게 솔직한 칭찬은 내 스타일이 아닌데, 국장이 함께 해줘서 더욱 빠져 버렸나 봐."
        },
        {
            "title": "일반 터치2",
            "filename": "File:vo_cab_gongzui_body_002.aac",
            "text": "이곳 역시 사교계의 현장이기에, 당연히 익숙한 탐욕이 넘쳐 흐르지. 하지만 환락에 빠져버린 욕망의 소용돌이야말로 순수한 영혼의 신선하고 담백한 본연의 맛을 드러내는 법, 이곳의 음식들은 각자의 별미를 지니고 있어. 이번에는 너도 부담 없이 즐겨봤으면 해."
        },
        {
            "title": "방치",
            "filename": "File:vo_cab_gongzui_idle_001.aac",
            "text": "음~ 음식을 즐기는 너의 모습, 정말 보기 좋아. 보고 있자면 정말 구미가 당긴다니까?"
        },
        {
            "title": "초조",
            "filename": "File:vo_cab_gongzui_clicking_001.aac",
            "text": "연회 같은 자리에서는 옷차림이 무척 중요해. 옷 스타일이나 코디 선택으로 연회 참석자의 매너, 교양, 사회적 지위를 알 수 있지. 그래서 내 드레스가 구긴다면, 나 진짜 화낼지도 몰라~"
        },
        {
            "title": "특별 주목",
            "filename": "File:vo_cab_gongzui_specialattention_001.aac",
            "text": "이렇게 날 졸졸 따라다니는 건, 음식에 대한 나의 평가를 믿어서야, 아니면 감독자로서의 책임을 다하기 위해서야? 뒤에서 따라오지만 말고, 내 손을 잡고 내 곁에 있어 줘. 이렇게 하면 내 모든 걸 직접 볼 수 있잖아?"
        }
    ],
    "crimson_prologue": [
        {
            "title": "스킨 획득",
            "filename": "File:vo_cab_yanhongxuyan_cacha_001.aac",
            "text": "마침, 오늘 밤의 연회에 '음미'할 줄 아는 손님이 한 명 모자랐어. 궁금해… 겹겹이 피어나는 그 선홍빛 아래에서, 넌 과연 무엇을 맛보게 될까?"
        },
        {
            "title": "레벨업",
            "filename": "File:vo_cab_yanhongxuyan_levelup_001.aac",
            "text": "열매가 탐스러울수록, 깨물리는 그 순간을 더 갈망하는 법이지. 달콤함과 아픔은 모두 그것의 숙명이니까."
        },
        {
            "title": "안부",
            "filename": "File:vo_cab_yanhongxuyan_greeting_001.aac",
            "text": "촛불이 숨 쉬고, 과즙이 떨어지며, 영혼이 떨리고 있어… 참 좋아, 난 이런 고요한 광기가 마음에 들어."
        },
        {
            "title": "일반 터치1",
            "filename": "File:vo_cab_yanhongxuyan_body_001.aac",
            "text": "아무리 단단한 돌이라 해도, 아무리 경건한 영혼이라 해도, 욕망에 오래 담가두면 결국엔 꿀이 스며 나오기 마련이야. 그러니 눈앞의 이 조각상들은, 그저 '성인'들이 스스로를 기만하며 남긴 기념물일 뿐이지."
        },
        {
            "title": "일반 터치2",
            "filename": "File:vo_cab_yanhongxuyan_body_002.aac",
            "text": "정말 절묘한 창조물이야… 단단한 껍질 아래엔, 영롱한 씨앗과 과육이 숨어 있지. 인내심을 가지고 섬세하게 가르지 않으면, 그 터져 나오는 달콤함을 맛볼 수 없어. 후후… 이런 과정은 티 없이 맑은 영혼을 음미하는 것과 아주 닮았어."
        },
        {
            "title": "방치",
            "filename": "File:vo_cab_yanhongxuyan_idle_001.aac",
            "text": "인내심은, 절정의 맛을 음미하기 전에 반드시 거쳐야 할 의식이지…"
        },
        {
            "title": "초조",
            "filename": "File:vo_cab_yanhongxuyan_clicking_001.aac",
            "text": "경솔한 손길은 연회에서 가장 흔한 어리석음이지. 하… 하지만 바로 그렇기에, 욕망이 더욱 솔직해 보이는 거야."
        },
        {
            "title": "특별 주목",
            "filename": "File:vo_cab_yanhongxuyan_specialattention_001.aac",
            "text": "네가 그렇게 바라보니까, 나도 헷갈려지네… 넌 날 감상하고 있는 걸까, 아니면 내가 음미해 주길 갈구하고 있는 걸까?"
        }
    ]
}